{
  "items": [
    {
      "id": 1,
      "name": "Yankee Candle",
      "description": "Usata, a metà.",
      "price": 15.5,
      "imgurl": "https://m0.her.ie/wp-content/uploads/2018/02/04134743/IMG_8789.jpg",
      "category": null,
      "owner": null
    },
    {
      "id": 2,
      "name": "Yankee Candle",
      "description": "Usata, a metà.",
      "price": 15.5,
      "imgurl": "https://m0.her.ie/wp-content/uploads/2018/02/04134743/IMG_8789.jpg",
      "category": null,
      "owner": null
    },
    {
      "id": 3,
      "name": "Yankee Candle",
      "description": "Usata, a metà.",
      "price": 15.5,
      "imgurl": "https://m0.her.ie/wp-content/uploads/2018/02/04134743/IMG_8789.jpg",
      "category": null,
      "owner": null
    },
    {
      "id": 4,
      "name": "Yankee Candle",
      "description": "Usata, a metà.",
      "price": 15.5,
      "imgurl": "https://m0.her.ie/wp-content/uploads/2018/02/04134743/IMG_8789.jpg",
      "category": null,
      "owner": null
    }
  ],
  "category": [
    {
      "id": 1,
      "name": "Casa",
      "description": "cose per la casa"
    }
  ],
  "users": [
    {
      "id": 1,
      "name": "Mariottide",
      "surname": "Rossi",
      "dob": "16-11-2021",
      "email": "mario.rossi@email.com"
    },
    {
      "id": 4,
      "name": "Roberto",
      "surname": "Verdicchi",
      "email": "roberto.verdi@gmail.com",
      "dob": "23-06-1980"
    },
    {
      "id": 5,
      "name": "barisla",
      "surname": "derraj",
      "email": "barilsidaderraj@gmail.com",
      "dob": "2022-12-31"
    },
    {
      "id": 6,
      "name": "Alessia",
      "surname": "Verdi",
      "email": "alessia.v@gmail.com",
      "dob": "1985-10-10"
    }
  ]
}